alu_8bit.v
// =====================================================================
// alu_8bit.v
// Synthesizable 8-bit Arithmetic Logic Unit (ALU)
//
// Supports 12 operations selected by a 4-bit opcode:
//   0000 ADD   : result = a + b
//   0001 SUB   : result = a - b
//   0010 AND   : result = a & b
//   0011 OR    : result = a | b
//   0100 XOR   : result = a ^ b
//   0101 NOR   : result = ~(a | b)
//   0110 SLL   : result = a << b[2:0]   (logical shift left)
//   0111 SRL   : result = a >> b[2:0]   (logical shift right)
//   1000 SRA   : result = a >>> b[2:0]  (arithmetic shift right)
//   1001 SLT   : result = (signed a < signed b) ? 1 : 0
//   1010 SLTU  : result = (unsigned a < unsigned b) ? 1 : 0
//   1011 NOT   : result = ~a
//   others     : result = 8'h00 (default/illegal opcode)
//
// Flags:
//   zero     - result == 0
//   negative - result[7] (MSB of result, two's-complement sign bit)
//   carry    - carry-out for ADD, NOT(borrow) for SUB, 0 otherwise
//   overflow - signed arithmetic overflow for ADD/SUB, 0 otherwise
// =====================================================================

module alu_8bit (
    input  wire [7:0] a,
    input  wire [7:0] b,
    input  wire [3:0] opcode,
    output reg  [7:0] result,
    output reg        carry,
    output reg        overflow,
    output wire        zero,
    output wire        negative
);

    localparam ADD  = 4'b0000;
    localparam SUB  = 4'b0001;
    localparam AND_OP = 4'b0010;
    localparam OR_OP  = 4'b0011;
    localparam XOR_OP = 4'b0100;
    localparam NOR_OP = 4'b0101;
    localparam SLL  = 4'b0110;
    localparam SRL  = 4'b0111;
    localparam SRA  = 4'b1000;
    localparam SLT  = 4'b1001;
    localparam SLTU = 4'b1010;
    localparam NOT_OP = 4'b1011;

    wire [8:0] add_ext = {1'b0, a} + {1'b0, b};
    wire [8:0] sub_ext = {1'b0, a} - {1'b0, b};

    assign zero     = (result == 8'h00);
    assign negative = result[7];

    always @(*) begin
        // Defaults every evaluation (avoids latch inference)
        result   = 8'h00;
        carry    = 1'b0;
        overflow = 1'b0;

        case (opcode)
            ADD: begin
                result   = add_ext[7:0];
                carry    = add_ext[8];
                // signed overflow: operands same sign, result different sign
                overflow = (a[7] == b[7]) && (result[7] != a[7]);
            end

            SUB: begin
                result   = sub_ext[7:0];
                carry    = ~sub_ext[8]; // carry=1 means no borrow (typical ALU convention)
                // signed overflow: operands different sign, result sign != a's sign
                overflow = (a[7] != b[7]) && (result[7] != a[7]);
            end

            AND_OP:  result = a & b;
            OR_OP:   result = a | b;
            XOR_OP:  result = a ^ b;
            NOR_OP:  result = ~(a | b);
            SLL:     result = a << b[2:0];
            SRL:     result = a >> b[2:0];
            SRA:     result = $signed(a) >>> b[2:0];
            SLT:     result = ($signed(a) < $signed(b)) ? 8'h01 : 8'h00;
            SLTU:    result = (a < b) ? 8'h01 : 8'h00;
            NOT_OP:  result = ~a;

            default: result = 8'h00;
        endcase
    end

endmodule

tb_alu_8bit.v
// =====================================================================
// tb_alu_8bit.v
// Self-checking testbench for alu_8bit
//   - Directed tests: cover every opcode plus key edge cases
//     (zero result, overflow, underflow/borrow, shifts by 0 and max,
//     signed comparisons, all-ones / all-zeros operands)
//   - Random tests: 200 randomized (a, b, opcode) vectors checked
//     against a behavioral reference model
//   - Tracks per-opcode coverage (each opcode hit at least once)
//   - Dumps a VCD waveform for visual inspection
// =====================================================================

`timescale 1ns/1ps

module tb_alu_8bit;

    reg  [7:0] a, b;
    reg  [3:0] opcode;
    wire [7:0] result;
    wire       carry, overflow, zero, negative;

    integer errors;
    integer tests;
    integer i;

    // opcode coverage tracking
    reg [11:0] opcode_hit; // bit per opcode 0..11

    alu_8bit dut (
        .a(a), .b(b), .opcode(opcode),
        .result(result), .carry(carry),
        .overflow(overflow), .zero(zero), .negative(negative)
    );

    // ---------------- Reference model ----------------
    task automatic ref_model;
        input  [7:0] ra, rb;
        input  [3:0] rop;
        output [7:0] rresult;
        output       rcarry, rover;
        reg [8:0] add_ext, sub_ext;
        begin
            add_ext = {1'b0, ra} + {1'b0, rb};
            sub_ext = {1'b0, ra} - {1'b0, rb};
            rcarry = 1'b0;
            rover  = 1'b0;
            case (rop)
                4'b0000: begin rresult = add_ext[7:0]; rcarry = add_ext[8];
                               rover = (ra[7]==rb[7]) && (rresult[7]!=ra[7]); end
                4'b0001: begin rresult = sub_ext[7:0]; rcarry = ~sub_ext[8];
                               rover = (ra[7]!=rb[7]) && (rresult[7]!=ra[7]); end
                4'b0010: rresult = ra & rb;
                4'b0011: rresult = ra | rb;
                4'b0100: rresult = ra ^ rb;
                4'b0101: rresult = ~(ra | rb);
                4'b0110: rresult = ra << rb[2:0];
                4'b0111: rresult = ra >> rb[2:0];
                4'b1000: rresult = $signed(ra) >>> rb[2:0];
                4'b1001: rresult = ($signed(ra) < $signed(rb)) ? 8'h01 : 8'h00;
                4'b1010: rresult = (ra < rb) ? 8'h01 : 8'h00;
                4'b1011: rresult = ~ra;
                default: rresult = 8'h00;
            endcase
        end
    endtask

    // ---------------- Check task ----------------
    task automatic check(input [127:0] label);
        reg [7:0] exp_result;
        reg       exp_carry, exp_over;
        begin
            ref_model(a, b, opcode, exp_result, exp_carry, exp_over);
            tests = tests + 1;
            if (opcode <= 11) opcode_hit[opcode] = 1'b1;
            #1; // allow combinational settle for $display ordering
            if (result !== exp_result || carry !== exp_carry || overflow !== exp_over) begin
                errors = errors + 1;
                $display("FAIL [%0s] a=%h b=%h op=%b | got result=%h carry=%b ovf=%b | exp result=%h carry=%b ovf=%b",
                          label, a, b, opcode, result, carry, overflow, exp_result, exp_carry, exp_over);
            end else begin
                $display("PASS [%0s] a=%h b=%h op=%b -> result=%h carry=%b ovf=%b zero=%b neg=%b",
                          label, a, b, opcode, result, carry, overflow, zero, negative);
            end
        end
    endtask

    task automatic apply(input [7:0] ta, input [7:0] tb, input [3:0] top, input [127:0] label);
        begin
            a = ta; b = tb; opcode = top;
            #5;
            check(label);
        end
    endtask

    initial begin
        $dumpfile("alu_wave.vcd");
        $dumpvars(0, tb_alu_8bit);

        errors = 0;
        tests  = 0;
        opcode_hit = 12'b0;

        $display("===================================================");
        $display(" DIRECTED TESTS");
        $display("===================================================");

        // ADD: basic, zero result, carry-out, signed overflow
        apply(8'h05, 8'h03, 4'b0000, "ADD_basic");
        apply(8'h00, 8'h00, 4'b0000, "ADD_zero");
        apply(8'hFF, 8'h01, 4'b0000, "ADD_carry_out");
        apply(8'h7F, 8'h01, 4'b0000, "ADD_signed_overflow"); // 127+1 overflows

        // SUB: basic, zero result, borrow, signed overflow
        apply(8'h05, 8'h03, 4'b0001, "SUB_basic");
        apply(8'h05, 8'h05, 4'b0001, "SUB_zero");
        apply(8'h00, 8'h01, 4'b0001, "SUB_borrow");
        apply(8'h80, 8'h01, 4'b0001, "SUB_signed_overflow"); // -128-1 overflows

        // Bitwise ops
        apply(8'hF0, 8'h0F, 4'b0010, "AND_disjoint");
        apply(8'hAA, 8'h55, 4'b0011, "OR_alternating");
        apply(8'hFF, 8'hFF, 4'b0100, "XOR_identical");
        apply(8'h00, 8'h00, 4'b0101, "NOR_all_zero");

        // Shifts: by 0 and by max (7)
        apply(8'h01, 8'h00, 4'b0110, "SLL_by_zero");
        apply(8'h01, 8'h07, 4'b0110, "SLL_by_max");
        apply(8'h80, 8'h07, 4'b0111, "SRL_by_max");
        apply(8'h80, 8'h01, 4'b1000, "SRA_negative_msb");

        // Comparisons
        apply(8'hFF, 8'h01, 4'b1001, "SLT_signed_neg_lt_pos"); // -1 < 1 -> true
        apply(8'h01, 8'hFF, 4'b1010, "SLTU_unsigned_lt");      // 1 < 255 -> true

        // NOT
        apply(8'h00, 8'h00, 4'b1011, "NOT_all_zero");
        apply(8'hFF, 8'h00, 4'b1011, "NOT_all_ones");

        // Illegal/undefined opcode -> default branch
        apply(8'hAA, 8'h55, 4'b1111, "UNDEFINED_opcode");

        $display("===================================================");
        $display(" RANDOM TESTS (200 vectors, opcodes 0-11)");
        $display("===================================================");
        for (i = 0; i < 200; i = i + 1) begin
            a = $random;
            b = $random;
            opcode = $unsigned($random) % 12; // restrict to defined opcodes 0-11
            #5;
            check("RANDOM");
        end

        $display("===================================================");
        $display(" SUMMARY");
        $display("===================================================");
        $display("Total checks run : %0d", tests);
        $display("Failures         : %0d", errors);
        $display("Opcode coverage  : %0d / 12 opcodes hit (mask=%b)",
                  count_ones(opcode_hit), opcode_hit);

        if (errors == 0)
            $display("RESULT: ALL TESTS PASSED");
        else
            $display("RESULT: %0d TEST(S) FAILED", errors);

        $finish;
    end

    function automatic integer count_ones(input [11:0] vec);
        integer k;
        begin
            count_ones = 0;
            for (k = 0; k < 12; k = k + 1)
                if (vec[k]) count_ones = count_ones + 1;
        end
    endfunction

endmodule

alu_wave.vcd
$date
	Sun Jun 21 16:39:29 2026
$end
$version
	Icarus Verilog
$end
$timescale
	1ps
$end
$scope module tb_alu_8bit $end
$var wire 1 ! zero $end
$var wire 8 " result [7:0] $end
$var wire 1 # overflow $end
$var wire 1 $ negative $end
$var wire 1 % carry $end
$var reg 8 & a [7:0] $end
$var reg 8 ' b [7:0] $end
$var reg 4 ( opcode [3:0] $end
$var reg 12 ) opcode_hit [11:0] $end
$var integer 32 * errors [31:0] $end
$var integer 32 + i [31:0] $end
$var integer 32 , tests [31:0] $end
$scope function count_ones $end
$upscope $end
$scope module dut $end
$var wire 8 - a [7:0] $end
$var wire 8 . b [7:0] $end
$var wire 4 / opcode [3:0] $end
$var wire 1 ! zero $end
$var wire 9 0 sub_ext [8:0] $end
$var wire 1 $ negative $end
$var wire 9 1 add_ext [8:0] $end
$var parameter 4 2 ADD $end
$var parameter 4 3 AND_OP $end
$var parameter 4 4 NOR_OP $end
$var parameter 4 5 NOT_OP $end
$var parameter 4 6 OR_OP $end
$var parameter 4 7 SLL $end
$var parameter 4 8 SLT $end
$var parameter 4 9 SLTU $end
$var parameter 4 : SRA $end
$var parameter 4 ; SRL $end
$var parameter 4 < SUB $end
$var parameter 4 = XOR_OP $end
$var reg 1 % carry $end
$var reg 1 # overflow $end
$var reg 8 > result [7:0] $end
$upscope $end
$scope task apply $end
$upscope $end
$scope task check $end
$upscope $end
$scope task ref_model $end
$upscope $end
$upscope $end
$enddefinitions $end
$comment Show the parameter values. $end
$dumpall
b100 =
b1 <
b111 ;
b1000 :
b1010 9
b1001 8
b110 7
b11 6
b1011 5
b101 4
b10 3
b0 2
$end
#0
$dumpvars
b1000 >
b1000 1
b10 0
b0 /
b11 .
b101 -
b0 ,
bx +
b0 *
b0 )
b0 (
b11 '
b101 &
0%
0$
0#
b1000 "
0!
$end
#5000
b1 )
b1 ,
#6000
1!
b0 "
b0 >
b0 '
b0 .
b0 1
b0 0
b0 &
b0 -
#11000
b10 ,
#12000
1%
b1 '
b1 .
b100000000 1
b11111110 0
b11111111 &
b11111111 -
#17000
b11 ,
#18000
1$
1#
0!
b10000000 "
b10000000 >
0%
b10000000 1
b1111110 0
b1111111 &
b1111111 -
#23000
b100 ,
#24000
0$
1%
0#
0!
b10 "
b10 >
b1 (
b1 /
b11 '
b11 .
b1000 1
b10 0
b101 &
b101 -
#29000
b11 )
b101 ,
#30000
1%
1!
b0 "
b0 >
b1010 1
b0 0
b101 '
b101 .
#35000
b110 ,
#36000
1$
0!
b11111111 "
b11111111 >
0%
b1 '
b1 .
b1 1
b111111111 0
b0 &
b0 -
#41000
b111 ,
#42000
0$
1#
1%
0!
b1111111 "
b1111111 >
b10000001 1
b1111111 0
b10000000 &
b10000000 -
#47000
b1000 ,
#48000
0#
0%
1!
b0 "
b0 >
b10 (
b10 /
b1111 '
b1111 .
b11111111 1
b11100001 0
b11110000 &
b11110000 -
#53000
b111 )
b1001 ,
#54000
1$
0!
b11111111 "
b11111111 >
b11 (
b11 /
b1010101 '
b1010101 .
b11111111 1
b1010101 0
b10101010 &
b10101010 -
#59000
b1111 )
b1010 ,
#60000
0$
1!
b0 "
b0 >
b100 (
b100 /
b11111111 '
b11111111 .
b111111110 1
b0 0
b11111111 &
b11111111 -
#65000
b11111 )
b1011 ,
#66000
1$
0!
b11111111 "
b11111111 >
b101 (
b101 /
b0 '
b0 .
b0 1
b0 0
b0 &
b0 -
#71000
b111111 )
b1100 ,
#72000
0$
0!
b1 "
b1 >
b110 (
b110 /
b1 1
b1 0
b1 &
b1 -
#77000
b1111111 )
b1101 ,
#78000
1$
0!
b10000000 "
b10000000 >
b1000 1
b111111010 0
b111 '
b111 .
#83000
b1110 ,
#84000
0$
0!
b1 "
b1 >
b111 (
b111 /
b10000111 1
b1111001 0
b10000000 &
b10000000 -
#89000
b11111111 )
b1111 ,
#90000
1$
0!
b11000000 "
b11000000 >
b1000 (
b1000 /
b10000001 1
b1111111 0
b1 '
b1 .
#95000
b111111111 )
b10000 ,
#96000
0$
0!
b1 "
b1 >
b1001 (
b1001 /
b100000000 1
b11111110 0
b11111111 &
b11111111 -
#101000
b1111111111 )
b10001 ,
#102000
0!
b1 "
b1 >
b1010 (
b1010 /
b11111111 '
b11111111 .
b100000000 1
b100000010 0
b1 &
b1 -
#107000
b11111111111 )
b10010 ,
#108000
1$
0!
b11111111 "
b11111111 >
b1011 (
b1011 /
b0 '
b0 .
b0 1
b0 0
b0 &
b0 -
#113000
b111111111111 )
b10011 ,
#114000
0$
1!
b0 "
b0 >
b11111111 1
b11111111 0
b11111111 &
b11111111 -
#119000
b10100 ,
#120000
b1111 (
b1111 /
b1010101 '
b1010101 .
b11111111 1
b1010101 0
b10101010 &
b10101010 -
#125000
b10101 ,
#126000
1$
1#
0!
b10100011 "
b10100011 >
b1 (
b1 /
b10000001 '
b10000001 .
b10100101 1
b110100011 0
b100100 &
b100100 -
b0 +
#131000
b10110 ,
#132000
0#
0!
b10010000 "
b10010000 >
b101 (
b101 /
b1101 '
b1101 .
b1110000 1
b1010110 0
b1100011 &
b1100011 -
b1 +
#137000
b10111 ,
#138000
0$
1!
b0 "
b0 >
b1001 (
b1001 /
b10010 '
b10010 .
b1110111 1
b1010011 0
b1100101 &
b1100101 -
b10 +
#143000
b11000 ,
#144000
1$
0!
b10000000 "
b10000000 >
b101 (
b101 /
b1110110 '
b1110110 .
b10000011 1
b110010111 0
b1101 &
b1101 -
b11 +
#149000
b11001 ,
#150000
0$
1%
0!
b1100001 "
b1100001 >
b1 (
b1 /
b10001100 '
b10001100 .
b101111001 1
b1100001 0
b11101101 &
b11101101 -
b100 +
#155000
b11010 ,
#156000
1$
0%
0!
b11000000 "
b11000000 >
b110 (
b110 /
b11000101 '
b11000101 .
b110001011 1
b1 0
b11000110 &
b11000110 -
b101 +
#161000
b11011 ,
#162000
0$
0!
b1100101 "
b1100101 >
b10 (
b10 /
b1110111 '
b1110111 .
b101011100 1
b1101110 0
b11100101 &
b11100101 -
b110 +
#167000
b11100 ,
#168000
0!
b111100 "
b111100 >
b110 (
b110 /
b11110010 '
b11110010 .
b110000001 1
b110011101 0
b10001111 &
b10001111 -
b111 +
#173000
b11101 ,
#174000
1$
0!
b11111111 "
b11111111 >
b1000 (
b1000 /
b11000101 '
b11000101 .
b110101101 1
b100011 0
b11101000 &
b11101000 -
b1000 +
#179000
b11110 ,
#180000
1%
0!
b10010000 "
b10010000 >
b1 (
b1 /
b101101 '
b101101 .
b11101010 1
b10010000 0
b10111101 &
b10111101 -
b1001 +
#185000
b11111 ,
#186000
0$
0%
0!
b11000 "
b11000 >
b1000 (
b1000 /
b1010 '
b1010 .
b1101101 1
b1011001 0
b1100011 &
b1100011 -
b1010 +
#191000
b100000 ,
#192000
1!
b0 "
b0 >
b1001 (
b1001 /
b10101010 '
b10101010 .
b11001010 1
b101110110 0
b100000 &
b100000 -
b1011 +
#197000
b100001 ,
#198000
1$
1%
0!
b10000011 "
b10000011 >
b1 (
b1 /
b10011 '
b10011 .
b10101001 1
b10000011 0
b10010110 &
b10010110 -
b1100 +
#203000
b100010 ,
#204000
0%
0!
b11101000 "
b11101000 >
b1101011 '
b1101011 .
b10111110 1
b111101000 0
b1010011 &
b1010011 -
b1101 +
#209000
b100011 ,
#210000
0$
1!
b0 "
b0 >
b1001 (
b1001 /
b10101110 '
b10101110 .
b10110000 1
b101010100 0
b10 &
b10 -
b1110 +
#215000
b100100 ,
#216000
0!
b11 "
b11 >
b10 (
b10 /
b100011 '
b100011 .
b11110010 1
b10101100 0
b11001111 &
b11001111 -
b1111 +
#221000
b100101 ,
#222000
0!
b1000 "
b1000 >
b111100 '
b111100 .
b100000110 1
b10001110 0
b11001010 &
b11001010 -
b10000 +
#227000
b100110 ,
#228000
1$
0!
b11001011 "
b11001011 >
b0 (
b0 /
b1000001 '
b1000001 .
b11001011 1
b1001001 0
b10001010 &
b10001010 -
b10001 +
#233000
b100111 ,
#234000
0$
0!
b111100 "
b111100 >
b111 (
b111 /
b10001001 '
b10001001 .
b100000001 1
b111101111 0
b1111000 &
b1111000 -
b10010 +
#239000
b101000 ,
#240000
0!
b1 "
b1 >
b1010 (
b1010 /
b11000110 '
b11000110 .
b101111100 1
b111110000 0
b10110110 &
b10110110 -
b10011 +
#245000
b101001 ,
#246000
1$
0!
b10111110 "
b10111110 >
b11 (
b11 /
b101010 '
b101010 .
b11100110 1
b10010010 0
b10111100 &
b10111100 -
b10100 +
#251000
b101010 ,
#252000
0$
0!
b11 "
b11 >
b111 (
b111 /
b10000101 '
b10000101 .
b11110110 1
b111101100 0
b1110001 &
b1110001 -
b10101 +
#257000
b101011 ,
#258000
1$
0!
b11101100 "
b11101100 >
b110 (
b110 /
b111010 '
b111010 .
b1110101 1
b1 0
b111011 &
b111011 -
b10110 +
#263000
b101100 ,
#264000
0$
0!
b100100 "
b100100 >
b1 (
b1 /
b11110001 '
b11110001 .
b100000110 1
b100100100 0
b10101 &
b10101 -
b10111 +
#269000
b101101 ,
#270000
0!
b110 "
b110 >
b111 (
b111 /
b1001100 '
b1001100 .
b10101110 1
b10110 0
b1100010 &
b1100010 -
b11000 +
#275000
b101110 ,
#276000
1$
0!
b10001111 "
b10001111 >
b11111000 '
b11111000 .
b110000111 1
b110010111 0
b10001111 &
b10001111 -
b11001 +
#281000
b101111 ,
#282000
0$
0!
b1100000 "
b1100000 >
b1011 (
b1011 /
b1011100 '
b1011100 .
b11111011 1
b1000011 0
b10011111 &
b10011111 -
b11010 +
#287000
b110000 ,
#288000
1$
0!
b11010010 "
b11010010 >
b0 (
b0 /
b1001001 '
b1001001 .
b11010010 1
b1000000 0
b10001001 &
b10001001 -
b11011 +
#293000
b110001 ,
#294000
0$
0!
b1010001 "
b1010001 >
b10 (
b10 /
b1010001 '
b1010001 .
b100101000 1
b10000110 0
b11010111 &
b11010111 -
b11100 +
#299000
b110010 ,
#300000
1$
0!
b11001110 "
b11001110 >
b0 (
b0 /
b11000010 '
b11000010 .
b11001110 1
b101001010 0
b1100 &
b1100 -
b11101 +
#305000
b110011 ,
#306000
0!
b11100000 "
b11100000 >
b110 (
b110 /
b111101 '
b111101 .
b10110100 1
b111010 0
b1110111 &
b1110111 -
b11110 +
#311000
b110100 ,
#312000
0!
b10000000 "
b10000000 >
b101 (
b101 /
b1101101 '
b1101101 .
b11101011 1
b10001 0
b1111110 &
b1111110 -
b11111 +
#317000
b110101 ,
#318000
0$
0!
b1001100 "
b1001100 >
b1 (
b1 /
b11010011 '
b11010011 .
b11110010 1
b101001100 0
b11111 &
b11111 -
b100000 +
#323000
b110110 ,
#324000
1$
0!
b10000100 "
b10000100 >
b101 (
b101 /
b1011011 '
b1011011 .
b11010011 1
b11101 0
b1111000 &
b1111000 -
b100001 +
#329000
b110111 ,
#330000
0$
0!
b1101001 "
b1101001 >
b0 (
b0 /
b101010 '
b101010 .
b1101001 1
b10101 0
b111111 &
b111111 -
b100010 +
#335000
b111000 ,
#336000
1#
1%
0!
b10100 "
b10100 >
b10001110 '
b10001110 .
b100010100 1
b111111000 0
b10000110 &
b10000110 -
b100011 +
#341000
b111001 ,
#342000
1$
0#
0%
0!
b11111110 "
b11111110 >
b11 (
b11 /
b100110 '
b100110 .
b100100000 1
b11010100 0
b11111010 &
b11111010 -
b100100 +
#347000
b111010 ,
#348000
0$
0!
b1011100 "
b1011100 >
b1011 (
b1011 /
b101111 '
b101111 .
b11010010 1
b1110100 0
b10100011 &
b10100011 -
b100101 +
#353000
b111011 ,
#354000
0!
b101 "
b101 >
b111 (
b111 /
b1000100 '
b1000100 .
b10100011 1
b11011 0
b1011111 &
b1011111 -
b100110 +
#359000
b111100 ,
#360000
0!
b1 "
b1 >
b1010 (
b1010 /
b11100110 '
b11100110 .
b110110001 1
b111100101 0
b11001011 &
b11001011 -
b100111 +
#365000
b111101 ,
#366000
0!
b1 "
b1 >
b11101101 '
b11101101 .
b100010110 1
b100111100 0
b101001 &
b101001 -
b101000 +
#371000
b111110 ,
#372000
1$
0!
b10011010 "
b10011010 >
b1011 (
b1011 /
b10110101 '
b10110101 .
b100011010 1
b110110000 0
b1100101 &
b1100101 -
b101001 +
#377000
b111111 ,
#378000
0$
0!
b111101 "
b111101 >
b100 (
b100 /
b1000100 '
b1000100 .
b10111101 1
b110101 0
b1111001 &
b1111001 -
b101010 +
#383000
b1000000 ,
#384000
0!
b1010000 "
b1010000 >
b110 (
b110 /
b10101011 '
b10101011 .
b11010101 1
b101111111 0
b101010 &
b101010 -
b101011 +
#389000
b1000001 ,
#390000
1%
0!
b1000010 "
b1000010 >
b1 (
b1 /
b10011010 '
b10011010 .
b101110110 1
b1000010 0
b11011100 &
b11011100 -
b101100 +
#395000
b1000010 ,
#396000
1$
0%
0!
b11000000 "
b11000000 >
b110 (
b110 /
b1010110 '
b1010110 .
b100011001 1
b1101101 0
b11000011 &
b11000011 -
b101101 +
#401000
b1000011 ,
#402000
0$
0!
b10 "
b10 >
b10 (
b10 /
b1010 '
b1010 .
b1110001 1
b1011101 0
b1100111 &
b1100111 -
b101110 +
#407000
b1000100 ,
#408000
0!
b1000001 "
b1000001 >
b100 (
b100 /
b1111001 '
b1111001 .
b10110001 1
b110111111 0
b111000 &
b111000 -
b101111 +
#413000
b1000101 ,
#414000
0!
b111 "
b111 >
b10010011 '
b10010011 .
b100100111 1
b1 0
b10010100 &
b10010100 -
b110000 +
#419000
b1000110 ,
#420000
1!
b0 "
b0 >
b1001 (
b1001 /
b11011011 '
b11011011 .
b100110100 1
b101111110 0
b1011001 &
b1011001 -
b110001 +
#425000
b1000111 ,
#426000
0!
b100000 "
b100000 >
b110 (
b110 /
b1101101 '
b1101101 .
b101000110 1
b1101100 0
b11011001 &
b11011001 -
b110010 +
#431000
b1001000 ,
#432000
1!
b0 "
b0 >
b1001 (
b1001 /
b10110110 '
b10110110 .
b110000000 1
b10100 0
b11001010 &
b11001010 -
b110011 +
#437000
b1001001 ,
#438000
1$
0!
b10111001 "
b10111001 >
b1011 (
b1011 /
b100 '
b100 .
b1001010 1
b1000010 0
b1000110 &
b1000110 -
b110100 +
#443000
b1001010 ,
#444000
0!
b11011101 "
b11011101 >
b100 (
b100 /
b10110100 '
b10110100 .
b100011101 1
b110110101 0
b1101001 &
b1101001 -
b110101 +
#449000
b1001011 ,
#450000
0!
b11010111 "
b11010111 >
b1011 (
b1011 /
b101101 '
b101101 .
b1010101 1
b111111011 0
b101000 &
b101000 -
b110110 +
#455000
b1001100 ,
#456000
0$
0!
b101110 "
b101110 >
b1000 (
b1000 /
b1000 '
b1000 .
b110110 1
b100110 0
b101110 &
b101110 -
b110111 +
#461000
b1001101 ,
#462000
1%
0!
b100110 "
b100110 >
b0 (
b0 /
b101001 '
b101001 .
b100100110 1
b11010100 0
b11111101 &
b11111101 -
b111000 +
#467000
b1001110 ,
#468000
0%
0!
b1 "
b1 >
b1001 (
b1001 /
b11011010 '
b11011010 .
b101100000 1
b110101100 0
b10000110 &
b10000110 -
b111001 +
#473000
b1001111 ,
#474000
0!
b1110110 "
b1110110 >
b11 (
b11 /
b1110000 '
b1110000 .
b11010110 1
b111110110 0
b1100110 &
b1100110 -
b111010 +
#479000
b1010000 ,
#480000
1$
0!
b10000000 "
b10000000 >
b110 (
b110 /
b1011110 '
b1011110 .
b100011000 1
b1011100 0
b10111010 &
b10111010 -
b111011 +
#485000
b1010001 ,
#486000
0$
0!
b1 "
b1 >
b1001 (
b1001 /
b11010 '
b11010 .
b11101111 1
b10111011 0
b11010101 &
b11010101 -
b111100 +
#491000
b1010010 ,
#492000
1$
0!
b11001101 "
b11001101 >
b0 (
b0 /
b10010110 '
b10010110 .
b11001101 1
b110100001 0
b110111 &
b110111 -
b111101 +
#497000
b1010011 ,
#498000
0$
1!
b0 "
b0 >
b1001 (
b1001 /
b10110110 '
b10110110 .
b11011100 1
b101110000 0
b100110 &
b100110 -
b111110 +
#503000
b1010100 ,
#504000
1#
1%
0!
b1100010 "
b1100010 >
b0 (
b0 /
b10000110 '
b10000110 .
b101100010 1
b1010110 0
b11011100 &
b11011100 -
b111111 +
#509000
b1010101 ,
#510000
1$
0#
0%
0!
b10000001 "
b10000001 >
b1011 (
b1011 /
b11011011 '
b11011011 .
b101011001 1
b110100011 0
b1111110 &
b1111110 -
b1000000 +
#515000
b1010110 ,
#516000
0$
1!
b0 "
b0 >
b1001 (
b1001 /
b11111010 '
b11111010 .
b101110011 1
b101111111 0
b1111001 &
b1111001 -
b1000001 +
#521000
b1010111 ,
#522000
0!
b101110 "
b101110 >
b110 (
b110 /
b10100001 '
b10100001 .
b10111000 1
b101110110 0
b10111 &
b10111 -
b1000010 +
#527000
b1011000 ,
#528000
0!
b1011011 "
b1011011 >
b1 (
b1 /
b11110101 '
b11110101 .
b101000101 1
b101011011 0
b1010000 &
b1010000 -
b1000011 +
#533000
b1011001 ,
#534000
1!
b0 "
b0 >
b1001 (
b1001 /
b11000001 '
b11000001 .
b11101010 1
b101101000 0
b101001 &
b101001 -
b1000100 +
#539000
b1011010 ,
#540000
0!
b1100111 "
b1100111 >
b1011 (
b1011 /
b1001011 '
b1001011 .
b11100011 1
b1001101 0
b10011000 &
b10011000 -
b1000101 +
#545000
b1011011 ,
#546000
1$
0!
b10110000 "
b10110000 >
b110 (
b110 /
b10001010 '
b10001010 .
b101110110 1
b1100010 0
b11101100 &
b11101100 -
b1000110 +
#551000
b1011100 ,
#552000
0$
0!
b1 "
b1 >
b1001 (
b1001 /
b10101001 '
b10101001 .
b101010001 1
b111111111 0
b10101000 &
b10101000 -
b1000111 +
#557000
b1011101 ,
#558000
1!
b0 "
b0 >
b111 (
b111 /
b11100110 '
b11100110 .
b11110100 1
b100101000 0
b1110 &
b1110 -
b1001000 +
#563000
b1011110 ,
#564000
1$
0!
b11010101 "
b11010101 >
b101 (
b101 /
b101010 '
b101010 .
b1010100 1
b0 0
b101010 &
b101010 -
b1001001 +
#569000
b1011111 ,
#570000
0$
0!
b1 "
b1 >
b1001 (
b1001 /
b111000 '
b111000 .
b11010110 1
b1100110 0
b10011110 &
b10011110 -
b1001010 +
#575000
b1100000 ,
#576000
1$
0!
b11001010 "
b11001010 >
b11 (
b11 /
b11001010 '
b11001010 .
b110010010 1
b111111110 0
b11001000 &
b11001000 -
b1001011 +
#581000
b1100001 ,
#582000
0$
0!
b1 "
b1 >
b1010 (
b1010 /
b11000111 '
b11000111 .
b100110010 1
b110100100 0
b1101011 &
b1101011 -
b1001100 +
#587000
b1100010 ,
#588000
1$
0!
b11110110 "
b11110110 >
b1 (
b1 /
b11000100 '
b11000100 .
b101111110 1
b111110110 0
b10111010 &
b10111010 -
b1001101 +
#593000
b1100011 ,
#594000
0$
0!
b1001 "
b1001 >
b111 (
b111 /
b10110100 '
b10110100 .
b101000110 1
b111011110 0
b10010010 &
b10010010 -
b1001110 +
#599000
b1100100 ,
#600000
0!
b11000 "
b11000 >
b110 (
b110 /
b11111010 '
b11111010 .
b110000000 1
b110001100 0
b10000110 &
b10000110 -
b1001111 +
#605000
b1100101 ,
#606000
0!
b1 "
b1 >
b1000 (
b1000 /
b10111101 '
b10111101 .
b11101111 1
b101110101 0
b110010 &
b110010 -
b1010000 +
#611000
b1100110 ,
#612000
0!
b10001 "
b10001 >
b101 (
b101 /
b11001010 '
b11001010 .
b110101110 1
b11010 0
b11100100 &
b11100100 -
b1010001 +
#617000
b1100111 ,
#618000
0!
b1011110 "
b1011110 >
b1011 (
b1011 /
b10001110 '
b10001110 .
b100101111 1
b10011 0
b10100001 &
b10100001 -
b1010010 +
#623000
b1101000 ,
#624000
0!
b11100 "
b11100 >
b1 (
b1 /
b11101111 '
b11101111 .
b11111010 1
b100011100 0
b1011 &
b1011 -
b1010011 +
#629000
b1101001 ,
#630000
0!
b1110111 "
b1110111 >
b11 (
b11 /
b1110101 '
b1110101 .
b10101011 1
b111000001 0
b110110 &
b110110 -
b1010100 +
#635000
b1101010 ,
#636000
0!
b1000 "
b1000 >
b10 (
b10 /
b10001000 '
b10001000 .
b11110011 1
b111100011 0
b1101011 &
b1101011 -
b1010101 +
#641000
b1101011 ,
#642000
1#
1%
0!
b101101 "
b101101 >
b0 (
b0 /
b10010010 '
b10010010 .
b100101101 1
b1001 0
b10011011 &
b10011011 -
b1010110 +
#647000
b1101100 ,
#648000
0#
0%
0!
b1 "
b1 >
b1010 (
b1010 /
b1001011 '
b1001011 .
b1111000 1
b111100010 0
b101101 &
b101101 -
b1010111 +
#653000
b1101101 ,
#654000
1!
b0 "
b0 >
b1000 (
b1000 /
b1101 '
b1101 .
b101011 1
b10001 0
b11110 &
b11110 -
b1011000 +
#659000
b1101110 ,
#660000
0!
b1 "
b1 >
b1010 (
b1010 /
b11010001 '
b11010001 .
b11101001 1
b101000111 0
b11000 &
b11000 -
b1011001 +
#665000
b1101111 ,
#666000
0!
b1000 "
b1000 >
b1000 (
b1000 /
b111011 '
b111011 .
b1111100 1
b110 0
b1000001 &
b1000001 -
b1011010 +
#671000
b1110000 ,
